picabot/__init__.py
picabot/picabot.py
picabot-0.1.2.dist-info/METADATA
picabot-0.1.2.dist-info/WHEEL
picabot-0.1.2.dist-info/licenses/LICENSE
picabot-0.1.2.dist-info/RECORD
