Metadata-Version: 2.3
Name: picabot
Version: 0.1.2
Summary: Library designed to ease the creation of bots for Picarto.
Project-URL: Homepage, https://github.com/NobreHD/picabot
Project-URL: Issues, https://github.com/NobreHD/picabot/issues
Author-email: NobreHD <info@nobrehd.pt>
License-File: LICENSE
Classifier: License :: OSI Approved :: GNU General Public License v3 or later (GPLv3+)
Classifier: Operating System :: OS Independent
Classifier: Programming Language :: Python :: 3
Requires-Python: >=3.6
Requires-Dist: websockets
